indium/__init__.py
indium/_confusables.py
indium/_exceptions.py
indium/_grapheme_data.py
indium/_scripts_data.py
indium/_unicode_data.py
indium/invisibles.py
indium/py.typed
indium/segments.py
indium/spoofing.py
elemental_indium-1.0.0.dist-info/METADATA
elemental_indium-1.0.0.dist-info/WHEEL
elemental_indium-1.0.0.dist-info/licenses/LICENSE
elemental_indium-1.0.0.dist-info/RECORD
